CHANGES.rst
COPYING
MANIFEST.in
README.rst
requirements-dev.txt
requirements.txt
setup.cfg
setup.py
pelican_feed_planet.egg-info/PKG-INFO
pelican_feed_planet.egg-info/SOURCES.txt
pelican_feed_planet.egg-info/dependency_links.txt
pelican_feed_planet.egg-info/not-zip-safe
pelican_feed_planet.egg-info/requires.txt
pelican_feed_planet.egg-info/top_level.txt
pelican_planet/__init__.py
pelican_planet/planet.py
pelican_planet/utils.py