Metadata-Version: 2.4
Name: pelican-feed-planet
Version: 0.24.0
Summary: Blog aggregator plugin for Pelican
Home-page: https://github.com/macbre/pelican-planet
Author: Mathieu Bridon
Author-email: bochecha@daitauha.fr
Classifier: Development Status :: 5 - Production/Stable
Requires-Python: >=3.9
License-File: COPYING
Requires-Dist: feedparser==6.0.12
Requires-Dist: Jinja2==3.1.6
Requires-Dist: pelican==4.11.0
Requires-Dist: python-dateutil==2.9.0.post0
Dynamic: author
Dynamic: author-email
Dynamic: classifier
Dynamic: description
Dynamic: description-content-type
Dynamic: home-page
Dynamic: license-file
Dynamic: requires-dist
Dynamic: requires-python
Dynamic: summary
